Workbook
Name aporte: Planilha1!$D$20
Name patrimonio_acumulado: Planilha1!$D$23
Name quantidade_anos: Planilha1!$D$21
Name rendimento_carteira: Planilha1!$D$13
Name salario: Planilha1!$D$12
Name sugestao_investimento: Planilha1!$D$14
Name taxa_mensal: Planilha1!$D$22
Name valor_total: Planilha1!$D$46

Sheet Planilha1
B11: CONFIGURAÇÕES
B12: Salário | D12: 5000
B13: Rendimento da Carteira | D13: 0.009
B14: Sugestão de Investimento | D14: =D12*30% -> 1500
B19: INVESTIMENTO MENSAL
B20: Quanto investir por mês? | D20: 500
B21: Por quantos anos? | D21: 5
B22: Taxa de Rendimento mensal? | D22: 0.01079
B23: Patrimônio acumulado? | D23: =FV(taxa_mensal,quantidade_anos*12,aporte*-1) -> 41888.457
B24: Dividendo Mensais? | D24: =patrimonio_acumulado*1% -> 418.88457
B27: CENÁRIOS | D27: Dividendos
A28: 2 | B28: Quanto em 2 Anos? | C28: =FV(Planilha1!$D$22,Planilha1!A28*12,Planilha1!$D$20*-1) -> 13613.814 | D28: =C28*rendimento_carteira -> 122.52432
A29: 5 | B29: Quanto em 5 Anos? | C29: =FV(Planilha1!$D$22,Planilha1!A29*12,Planilha1!$D$20*-1) -> 41888.457 | D29: =C29*rendimento_carteira -> 376.99611
A30: 10 | B30: Quanto em 10 Anos? | C30: =FV(Planilha1!$D$22,Planilha1!A30*12,Planilha1!$D$20*-1) -> 121642.11 | D30: =C30*rendimento_carteira -> 1094.779
A31: 20 | B31: Quanto em 20 Anos? | C31: =FV(Planilha1!$D$22,Planilha1!A31*12,Planilha1!$D$20*-1) -> 562599.2 | D31: =C31*rendimento_carteira -> 5063.3928
A32: 30 | B32: Quanto em 30 Anos³ | C32: =FV(Planilha1!$D$22,Planilha1!A32*12,Planilha1!$D$20*-1) -> 2161084.8 | D32: =C32*rendimento_carteira -> 19449.763
B35: PERFIL | C35: Conservador
B36: VALOR A SER INVESTIDO POR MÊS | C36: =aporte -> 500
B39: TIPO DE FII | C39: Percentual Sugerido | D39: Valores
B40: PAPEL | C40: =VLOOKUP($C$35&"-"&B40,Planilha2!$B:$E,4,FALSE) -> 0.3 | D40: =C40*$C$36 -> 150
B41: TIJOLO | C41: =VLOOKUP($C$35&"-"&B41,Planilha2!$B:$E,4,FALSE) -> 0.5 | D41: =C41*$C$36 -> 250
B42: HIBRIDOS | C42: =VLOOKUP($C$35&"-"&B42,Planilha2!$B:$E,4,FALSE) -> 0.1 | D42: =C42*$C$36 -> 50
B43: FOFs | C43: =VLOOKUP($C$35&"-"&B43,Planilha2!$B:$E,4,FALSE) -> 0.1 | D43: =C43*$C$36 -> 50
B44: DESENVOLVIMENTO | C44: =VLOOKUP($C$35&"-"&B44,Planilha2!$B:$E,4,FALSE) -> 0 | D44: =C44*$C$36 -> 0
B45: HOTELARIAS | C45: =VLOOKUP($C$35&"-"&B45,Planilha2!$B:$E,4,FALSE) -> 0 | D45: =C45*$C$36 -> 0
D46: =SUM(D40:D45) -> 500

Sheet Planilha2
B3: CHAVE | C3: PERFIL | D3: TIPO DE FII | E3: PERCENTUAL | H3: %
B4: =C4&"-"&D4 -> Conservador-PAPEL | C4: Conservador | D4: PAPEL | E4: 0.3 | G4: Moderado-TIJOLO | H4: =VLOOKUP(G4,$B:$E,4,FALSE) -> 0.4
B5: =C5&"-"&D5 -> Conservador-TIJOLO | C5: Conservador | D5: TIJOLO | E5: 0.5
B6: =C6&"-"&D6 -> Conservador-HIBRIDOS | C6: Conservador | D6: HIBRIDOS | E6: 0.1
B7: =C7&"-"&D7 -> Conservador-FOFs | C7: Conservador | D7: FOFs | E7: 0.1
B8: =C8&"-"&D8 -> Conservador-DESENVOLVIMENTO | C8: Conservador | D8: DESENVOLVIMENTO | E8: 0
B9: =C9&"-"&D9 -> Conservador-HOTELARIAS | C9: Conservador | D9: HOTELARIAS | E9: 0
B10: =C10&"-"&D10 -> Moderado-PAPEL | C10: Moderado | D10: PAPEL | E10: 0.31
B11: =C11&"-"&D11 -> Moderado-TIJOLO | C11: Moderado | D11: TIJOLO | E11: 0.4
B12: =C12&"-"&D12 -> Moderado-HIBRIDOS | C12: Moderado | D12: HIBRIDOS | E12: 0.08
B13: =C13&"-"&D13 -> Moderado-FOFs | C13: Moderado | D13: FOFs | E13: 0.1
B14: =C14&"-"&D14 -> Moderado-DESENVOLVIMENTO | C14: Moderado | D14: DESENVOLVIMENTO | E14: 0.01
B15: =C15&"-"&D15 -> Moderado-HOTELARIAS | C15: Moderado | D15: HOTELARIAS | E15: 0.1
B16: =C16&"-"&D16 -> Agressivo-PAPEL | C16: Agressivo | D16: PAPEL | E16: 0.5
... B21: =C21&"-"&D21 -> Agressivo-HOTELARIAS | C21: Agressivo | D21: HOTELARIAS | E21: 0.1
